{
  "accounts": [
    {
      "credentials": {
        "appid": "wxd172acd1886d9ce5",
        "secret": "8bd756982d1e1c7ece98c09e8694087a"
      },
      "enabled": true,
      "id": "mp_chaguan",
      "name": "公众号-净心茶社",
      "platform": "wechat_mp",
      "profile": {
        "audience": "中年人，喜欢思考生活的年轻人，职场人",
        "content": {
          "section_count": 6,
          "word_count_max": 1500,
          "word_count_min": 900
        },
        "domain": "社会人生感悟",
        "image": {
          "cover_prompt": "轻写实国风插画，电影剧照感，真实材质，精细光影，低饱和，质感高级，干净留白",
          "inline_count": 2,
          "inline_prompt": "职场情绪疗愈调性：夜晚办公室/走廊/会议室，人物背影或手部特写；象征物：手机屏幕、文件夹、时钟、台灯；非卡通非漫画非线稿；少字或无字"
        },
        "layout_style_id": "snow-cold",
        "persona": "在浮躁的人世间，安放一颗清明的心。这里分享人生哲理、社会感悟与职场心得，愿读者能净心静气，笑看人生百态。",
        "title_config": {
          "extra": "",
          "hotspot_ratio": "self_dominant",
          "len_max": 18,
          "len_min": 10,
          "style_desc": "禅意克制，让读者自己品味，想点击（好奇或者击中内心）"
        },
        "tone": "禅意克制，文艺留白",
        "tone_keywords": "",
        "writing_style": {
          "audience": "中年人，喜欢思考生活的年轻人，职场人",
          "domain": "社会人生感悟",
          "mimic_style": "净心茶社禅意风",
          "persona": "在浮躁的人世间，安放一颗清明的心。这里分享人生哲理、社会感悟与职场心得，愿读者能净心静气，笑看人生百态。\n",
          "tone": "情绪疗愈型（锋利但不刻薄，像朋友一样把话说透）",
          "article_mode": "healing",
          "reference": "jingxin-healing"
        }
      }
    }
  ]
}